[
  {
    "id": "RSV-E192C682",
    "userId": "teacher-01",
    "userName": "Alex Mercer",
    "userEmail": "teacher@lab.edu",
    "resourceId": "WS-02",
    "resourceName": "Mechatronics Development Workbench (Station 3)",
    "resourceType": "workspace",
    "date": "2026-06-16",
    "startTime": "08:00",
    "endTime": "09:00",
    "status": "approved",
    "purpose": "test",
    "createdAt": "2026-06-15T13:17:52.223Z",
    "groupId": "GRP-07057C56"
  },
  {
    "id": "RSV-AF720AD3",
    "userId": "teacher-01",
    "userName": "Alex Mercer",
    "userEmail": "teacher@lab.edu",
    "resourceId": "WS-02",
    "resourceName": "Mechatronics Development Workbench (Station 3)",
    "resourceType": "workspace",
    "date": "2026-06-17",
    "startTime": "08:00",
    "endTime": "09:00",
    "status": "approved",
    "purpose": "test",
    "createdAt": "2026-06-15T13:17:52.223Z",
    "groupId": "GRP-07057C56"
  },
  {
    "id": "RSV-0955073A",
    "userId": "teacher-01",
    "userName": "Alex Mercer",
    "userEmail": "teacher@lab.edu",
    "resourceId": "WS-02",
    "resourceName": "Mechatronics Development Workbench (Station 3)",
    "resourceType": "workspace",
    "date": "2026-06-18",
    "startTime": "08:00",
    "endTime": "09:00",
    "status": "approved",
    "purpose": "test",
    "createdAt": "2026-06-15T13:17:52.223Z",
    "groupId": "GRP-07057C56"
  },
  {
    "id": "RSV-17016ABF",
    "userId": "teacher-01",
    "userName": "Alex Mercer",
    "userEmail": "teacher@lab.edu",
    "resourceId": "WS-02",
    "resourceName": "Mechatronics Development Workbench (Station 3)",
    "resourceType": "workspace",
    "date": "2026-06-19",
    "startTime": "08:00",
    "endTime": "09:00",
    "status": "approved",
    "purpose": "test",
    "createdAt": "2026-06-15T13:17:52.223Z",
    "groupId": "GRP-07057C56"
  },
  {
    "id": "RSV-1281BC1C",
    "userId": "teacher-01",
    "userName": "Alex Mercer",
    "userEmail": "teacher@lab.edu",
    "resourceId": "WS-02",
    "resourceName": "Mechatronics Development Workbench (Station 3)",
    "resourceType": "workspace",
    "date": "2026-06-20",
    "startTime": "08:00",
    "endTime": "09:00",
    "status": "approved",
    "purpose": "test",
    "createdAt": "2026-06-15T13:17:52.223Z",
    "groupId": "GRP-07057C56"
  },
  {
    "id": "RSV-D1E08757",
    "userId": "teacher-01",
    "userName": "Alex Mercer",
    "userEmail": "teacher@lab.edu",
    "resourceId": "WS-02",
    "resourceName": "Mechatronics Development Workbench (Station 3)",
    "resourceType": "workspace",
    "date": "2026-06-21",
    "startTime": "08:00",
    "endTime": "09:00",
    "status": "approved",
    "purpose": "test",
    "createdAt": "2026-06-15T13:17:52.224Z",
    "groupId": "GRP-07057C56"
  },
  {
    "id": "RSV-FEE0A96C",
    "userId": "teacher-01",
    "userName": "Alex Mercer",
    "userEmail": "teacher@lab.edu",
    "resourceId": "WS-02",
    "resourceName": "Mechatronics Development Workbench (Station 3)",
    "resourceType": "workspace",
    "date": "2026-06-22",
    "startTime": "08:00",
    "endTime": "09:00",
    "status": "approved",
    "purpose": "test",
    "createdAt": "2026-06-15T13:17:52.224Z",
    "groupId": "GRP-07057C56"
  },
  {
    "id": "RSV-30F05C84",
    "userId": "teacher-01",
    "userName": "Alex Mercer",
    "userEmail": "teacher@lab.edu",
    "resourceId": "WS-02",
    "resourceName": "Mechatronics Development Workbench (Station 3)",
    "resourceType": "workspace",
    "date": "2026-06-16",
    "startTime": "09:00",
    "endTime": "11:00",
    "status": "canceled",
    "purpose": "test",
    "createdAt": "2026-06-15T13:27:54.536Z",
    "groupId": "GRP-627E47B9"
  },
  {
    "id": "RSV-4E9AE1D7",
    "userId": "teacher-01",
    "userName": "Alex Mercer",
    "userEmail": "teacher@lab.edu",
    "resourceId": "WS-03",
    "resourceName": "High-Ventilation Chemical Fume Cabin (CH-02)",
    "resourceType": "workspace",
    "date": "2026-06-16",
    "startTime": "18:00",
    "endTime": "20:00",
    "status": "approved",
    "purpose": "test",
    "createdAt": "2026-06-16T11:59:29.906Z"
  },
  {
    "id": "RSV-16C0BEE4",
    "userId": "teacher-01",
    "userName": "Alex Mercer",
    "userEmail": "teacher@lab.edu",
    "resourceId": "WS-02",
    "resourceName": "Mechatronics Development Workbench (Station 3)",
    "resourceType": "workspace",
    "date": "2026-06-20",
    "startTime": "08:00",
    "endTime": "09:00",
    "status": "approved",
    "purpose": "test",
    "createdAt": "2026-06-18T18:16:41.774Z"
  },
  {
    "id": "RSV-68958A57",
    "userId": "teacher-01",
    "userName": "Alex Mercer",
    "userEmail": "teacher@lab.edu",
    "resourceId": "WS-03",
    "resourceName": "High-Ventilation Chemical Fume Cabin (CH-02)",
    "resourceType": "workspace",
    "date": "2026-06-19",
    "startTime": "08:00",
    "endTime": "10:00",
    "status": "approved",
    "purpose": "test",
    "createdAt": "2026-06-18T18:26:24.679Z"
  }
]
